{
  "Title": "Paths of Glory",
  "Year": "1957",
  "Rated": "Approved",
  "Released": "25 Dec 1957",
  "Runtime": "88 min",
  "Genre": "Drama, War",
  "Director": "Stanley Kubrick",
  "Writer": "Stanley Kubrick, Calder Willingham, Jim Thompson",
  "Actors": "Kirk Douglas, Ralph Meeker, Adolphe Menjou",
  "Plot": "After a failed attack on a German position, a general orders three soldiers, chosen at random, court-martialed for cowardice and their commanding officer must defend them.",
  "Language": "English, German, Latin",
  "Country": "United States",
  "Awards": "Nominated for 1 BAFTA Award5 wins & 3 nominations total",
  "Poster": "https://m.media-amazon.com/images/M/MV5BOTI5Nzc0OTMtYzBkMS00NjkxLThmM2UtNjM2ODgxN2M5NjNkXkEyXkFqcGdeQXVyNjQ2MjQ5NzM@._V1_SX300.jpg",
  "Ratings": [
    {
      "Source": "Internet Movie Database",
      "Value": "8.4/10"
    },
    {
      "Source": "Rotten Tomatoes",
      "Value": "96%"
    },
    {
      "Source": "Metacritic",
      "Value": "90/100"
    }
  ],
  "Metascore": "90",
  "imdbRating": "8.4",
  "imdbVotes": "214,400",
  "imdbID": "tt0050825",
  "Type": "movie",
  "DVD": "N/A",
  "BoxOffice": "N/A",
  "Production": "N/A",
  "Website": "N/A",
  "Response": "True"
}