{
  "Title": "The Vast of Night",
  "Year": "2019",
  "Rated": "PG-13",
  "Released": "29 May 2020",
  "Runtime": "91 min",
  "Genre": "Drama, Mystery, Sci-Fi",
  "Director": "Andrew Patterson",
  "Writer": "Andrew Patterson, Craig W. Sanger",
  "Actors": "Sierra McCormick, Jake Horowitz, Gail Cronauer",
  "Plot": "One night in New Mexico, in the late 1950s, a switchboard operator and radio DJ discover a strange audio frequency which could change the future forever.",
  "Language": "English",
  "Country": "United States",
  "Awards": "12 wins & 43 nominations",
  "Poster": "https://m.media-amazon.com/images/M/MV5BY2YxNDczNGYtNmViNi00MDZiLWJiM2ItNGFlN2Q1NGExNGZhXkEyXkFqcGdeQXVyODE0OTU5Nzg@._V1_SX300.jpg",
  "Ratings": [
    {
      "Source": "Internet Movie Database",
      "Value": "6.7/10"
    },
    {
      "Source": "Rotten Tomatoes",
      "Value": "92%"
    },
    {
      "Source": "Metacritic",
      "Value": "84/100"
    }
  ],
  "Metascore": "84",
  "imdbRating": "6.7",
  "imdbVotes": "45,286",
  "imdbID": "tt6803046",
  "Type": "movie",
  "DVD": "N/A",
  "BoxOffice": "N/A",
  "Production": "N/A",
  "Website": "N/A",
  "Response": "True"
}